{
  "config": "{\"version\":\"5.68\",\"themeCollection\":{\"baseTheme\":{\"name\":\"CY25SU11\",\"version\":{\"visual\":\"2.4.0\",\"report\":\"3.0.0\",\"page\":\"2.3.0\"},\"type\":2}},\"activeSectionIndex\":1,\"defaultDrillFilterOtherVisuals\":true,\"settings\":{\"useNewFilterPaneExperience\":true,\"allowChangeFilterTypes\":true,\"useStylableVisualContainerHeader\":true,\"queryLimitOption\":6,\"useEnhancedTooltips\":true,\"exportDataMode\":1,\"useDefaultAggregateDisplayName\":true},\"objects\":{\"section\":[{\"properties\":{\"verticalAlignment\":{\"expr\":{\"Literal\":{\"Value\":\"'Top'\"}}}}}],\"outspacePane\":[{\"properties\":{\"expanded\":{\"expr\":{\"Literal\":{\"Value\":\"false\"}}}}}]}}",
  "layoutOptimization": 0,
  "resourcePackages": [
    {
      "resourcePackage": {
        "disabled": false,
        "items": [
          {
            "name": "CY25SU11",
            "path": "BaseThemes/CY25SU11.json",
            "type": 202
          }
        ],
        "name": "SharedResources",
        "type": 2
      }
    }
  ],
  "sections": [
    {
      "config": "{\"objects\":{\"background\":[{\"properties\":{\"color\":{\"solid\":{\"color\":{\"expr\":{\"Literal\":{\"Value\":\"'#FFFFFF'\"}}}}},\"transparency\":{\"expr\":{\"Literal\":{\"Value\":\"60L\"}}}}}]},\"howCreated\":\"Copilot\"}",
      "displayName": "Overview",
      "displayOption": 1,
      "filters": "[]",
      "height": 720.00,
      "name": "48fc2da32602de485594",
      "ordinal": 1,
      "visualContainers": [
        {
          "config": "{\"name\":\"28267318892ae890b730\",\"layouts\":[{\"id\":0,\"position\":{\"x\":645,\"y\":456,\"z\":1,\"width\":595,\"height\":224}}],\"singleVisual\":{\"visualType\":\"tableEx\",\"projections\":{\"Values\":[{\"queryRef\":\"customer.FirstName\"},{\"queryRef\":\"customer.LastName\"},{\"queryRef\":\"customer.EmailAddress\"},{\"queryRef\":\"sales.TotalRevenue\"}]},\"prototypeQuery\":{\"Version\":2,\"From\":[{\"Name\":\"c\",\"Entity\":\"customer\",\"Type\":0},{\"Name\":\"s\",\"Entity\":\"sales\",\"Type\":0}],\"Select\":[{\"Column\":{\"Expression\":{\"SourceRef\":{\"Source\":\"c\"}},\"Property\":\"FirstName\"},\"Name\":\"customer.FirstName\"},{\"Column\":{\"Expression\":{\"SourceRef\":{\"Source\":\"c\"}},\"Property\":\"LastName\"},\"Name\":\"customer.LastName\"},{\"Column\":{\"Expression\":{\"SourceRef\":{\"Source\":\"c\"}},\"Property\":\"EmailAddress\"},\"Name\":\"customer.EmailAddress\"},{\"Measure\":{\"Expression\":{\"SourceRef\":{\"Source\":\"s\"}},\"Property\":\"TotalRevenue\"},\"Name\":\"sales.TotalRevenue\"}],\"OrderBy\":[{\"Direction\":2,\"Expression\":{\"Measure\":{\"Expression\":{\"SourceRef\":{\"Source\":\"s\"}},\"Property\":\"TotalRevenue\"}}}]},\"drillFilterOtherVisuals\":true,\"objects\":{},\"vcObjects\":{\"dropShadow\":[{\"properties\":{\"show\":{\"expr\":{\"Literal\":{\"Value\":\"true\"}}},\"color\":{\"solid\":{\"color\":{\"expr\":{\"Literal\":{\"Value\":\"'#A6ADC6'\"}}}}},\"preset\":{\"expr\":{\"Literal\":{\"Value\":\"'Custom'\"}}},\"shadowSpread\":{\"expr\":{\"Literal\":{\"Value\":\"0L\"}}},\"shadowBlur\":{\"expr\":{\"Literal\":{\"Value\":\"5L\"}}},\"angle\":{\"expr\":{\"Literal\":{\"Value\":\"90L\"}}},\"shadowDistance\":{\"expr\":{\"Literal\":{\"Value\":\"4L\"}}},\"transparency\":{\"expr\":{\"Literal\":{\"Value\":\"85L\"}}}}}],\"background\":[{\"properties\":{\"show\":{\"expr\":{\"Literal\":{\"Value\":\"true\"}}}}}],\"border\":[{\"properties\":{\"show\":{\"expr\":{\"Literal\":{\"Value\":\"true\"}}},\"color\":{\"solid\":{\"color\":{\"expr\":{\"Literal\":{\"Value\":\"'#E0E0E0'\"}}}}},\"radius\":{\"expr\":{\"Literal\":{\"Value\":\"4L\"}}}}}]}},\"howCreated\":\"Copilot\"}",
          "filters": "[{\"name\":\"b9173f68e36e88ed0d66\",\"filter\":{\"Version\":2,\"From\":[{\"Name\":\"c\",\"Entity\":\"customer\",\"Type\":0},{\"Name\":\"s\",\"Entity\":\"sales\",\"Type\":0}],\"Where\":[{\"Condition\":{\"Exists\":{\"Expression\":{\"SourceRef\":{\"Source\":\"c\"}}}},\"Target\":[{\"SourceRef\":{\"Source\":\"s\"}}]}]},\"type\":\"Passthrough\",\"restatement\":\"Sales that have customers\",\"howCreated\":1}]",
          "height": 224.00,
          "width": 595.00,
          "x": 645.00,
          "y": 456.00,
          "z": 1.00
        },
        {
          "config": "{\"name\":\"33d494090b00ddd1d7eb\",\"layouts\":[{\"id\":0,\"position\":{\"x\":840,\"y\":0,\"z\":2,\"width\":212,\"height\":72}}],\"singleVisual\":{\"visualType\":\"slicer\",\"projections\":{\"Values\":[{\"queryRef\":\"product.CategoryName\",\"active\":true}]},\"prototypeQuery\":{\"Version\":2,\"From\":[{\"Name\":\"p\",\"Entity\":\"product\",\"Type\":0}],\"Select\":[{\"Column\":{\"Expression\":{\"SourceRef\":{\"Source\":\"p\"}},\"Property\":\"CategoryName\"},\"Name\":\"product.CategoryName\",\"NativeReferenceName\":\"CategoryName\"}]},\"drillFilterOtherVisuals\":true,\"objects\":{\"data\":[{\"properties\":{\"mode\":{\"expr\":{\"Literal\":{\"Value\":\"'Dropdown'\"}}}}}],\"header\":[{\"properties\":{\"show\":{\"expr\":{\"Literal\":{\"Value\":\"true\"}}},\"fontFamily\":{\"expr\":{\"Literal\":{\"Value\":\"'Segoe UI'\"}}},\"textSize\":{\"expr\":{\"Literal\":{\"Value\":\"9L\"}}}}}],\"selection\":[{\"properties\":{\"selectAllCheckboxEnabled\":{\"expr\":{\"Literal\":{\"Value\":\"true\"}}}}}],\"items\":[{\"properties\":{\"textSize\":{\"expr\":{\"Literal\":{\"Value\":\"9L\"}}}}}]},\"vcObjects\":{\"dropShadow\":[{\"properties\":{\"show\":{\"expr\":{\"Literal\":{\"Value\":\"true\"}}},\"color\":{\"solid\":{\"color\":{\"expr\":{\"Literal\":{\"Value\":\"'#A6ADC6'\"}}}}},\"preset\":{\"expr\":{\"Literal\":{\"Value\":\"'Custom'\"}}},\"shadowSpread\":{\"expr\":{\"Literal\":{\"Value\":\"0L\"}}},\"shadowBlur\":{\"expr\":{\"Literal\":{\"Value\":\"5L\"}}},\"angle\":{\"expr\":{\"Literal\":{\"Value\":\"90L\"}}},\"shadowDistance\":{\"expr\":{\"Literal\":{\"Value\":\"4L\"}}},\"transparency\":{\"expr\":{\"Literal\":{\"Value\":\"85L\"}}}}}],\"background\":[{\"properties\":{\"show\":{\"expr\":{\"Literal\":{\"Value\":\"true\"}}}}}],\"border\":[{\"properties\":{\"show\":{\"expr\":{\"Literal\":{\"Value\":\"true\"}}},\"color\":{\"solid\":{\"color\":{\"expr\":{\"Literal\":{\"Value\":\"'#E0E0E0'\"}}}}},\"radius\":{\"expr\":{\"Literal\":{\"Value\":\"4L\"}}}}}],\"padding\":[{\"properties\":{\"top\":{\"expr\":{\"Literal\":{\"Value\":\"2L\"}}},\"bottom\":{\"expr\":{\"Literal\":{\"Value\":\"0L\"}}},\"left\":{\"expr\":{\"Literal\":{\"Value\":\"0L\"}}},\"right\":{\"expr\":{\"Literal\":{\"Value\":\"0L\"}}}}}]}},\"howCreated\":\"Copilot\"}",
          "filters": "[]",
          "height": 72.00,
          "width": 212.00,
          "x": 840.00,
          "y": 0.00,
          "z": 2.00
        },
        {
          "config": "{\"name\":\"559c7953bba40440a9b5\",\"layouts\":[{\"id\":0,\"position\":{\"x\":40,\"y\":100,\"z\":1,\"width\":595,\"height\":112}}],\"singleVisual\":{\"visualType\":\"card\",\"projections\":{\"Values\":[{\"queryRef\":\"sales.TotalRevenue\"}]},\"prototypeQuery\":{\"Version\":2,\"From\":[{\"Name\":\"s\",\"Entity\":\"sales\",\"Type\":0}],\"Select\":[{\"Measure\":{\"Expression\":{\"SourceRef\":{\"Source\":\"s\"}},\"Property\":\"TotalRevenue\"},\"Name\":\"sales.TotalRevenue\"}]},\"drillFilterOtherVisuals\":true,\"objects\":{\"labels\":[{\"properties\":{\"labelDisplayUnits\":{\"expr\":{\"Literal\":{\"Value\":\"1L\"}}}}}]},\"vcObjects\":{\"dropShadow\":[{\"properties\":{\"show\":{\"expr\":{\"Literal\":{\"Value\":\"true\"}}},\"color\":{\"solid\":{\"color\":{\"expr\":{\"Literal\":{\"Value\":\"'#A6ADC6'\"}}}}},\"preset\":{\"expr\":{\"Literal\":{\"Value\":\"'Custom'\"}}},\"shadowSpread\":{\"expr\":{\"Literal\":{\"Value\":\"0L\"}}},\"shadowBlur\":{\"expr\":{\"Literal\":{\"Value\":\"5L\"}}},\"angle\":{\"expr\":{\"Literal\":{\"Value\":\"90L\"}}},\"shadowDistance\":{\"expr\":{\"Literal\":{\"Value\":\"4L\"}}},\"transparency\":{\"expr\":{\"Literal\":{\"Value\":\"85L\"}}}}}],\"background\":[{\"properties\":{\"show\":{\"expr\":{\"Literal\":{\"Value\":\"true\"}}}}}],\"border\":[{\"properties\":{\"show\":{\"expr\":{\"Literal\":{\"Value\":\"true\"}}},\"color\":{\"solid\":{\"color\":{\"expr\":{\"Literal\":{\"Value\":\"'#E0E0E0'\"}}}}},\"radius\":{\"expr\":{\"Literal\":{\"Value\":\"4L\"}}}}}]}},\"howCreated\":\"Copilot\"}",
          "filters": "[]",
          "height": 112.00,
          "width": 595.00,
          "x": 40.00,
          "y": 100.00,
          "z": 1.00
        },
        {
          "config": "{\"name\":\"5ed224bc030e864a7309\",\"layouts\":[{\"id\":0,\"position\":{\"x\":40,\"y\":456,\"z\":1,\"width\":595,\"height\":224}}],\"singleVisual\":{\"visualType\":\"clusteredBarChart\",\"projections\":{\"Category\":[{\"queryRef\":\"address.CountryRegion\"}],\"Y\":[{\"queryRef\":\"sales.TotalRevenue\"}]},\"prototypeQuery\":{\"Version\":2,\"From\":[{\"Name\":\"a\",\"Entity\":\"address\",\"Type\":0},{\"Name\":\"s\",\"Entity\":\"sales\",\"Type\":0}],\"Select\":[{\"Column\":{\"Expression\":{\"SourceRef\":{\"Source\":\"a\"}},\"Property\":\"CountryRegion\"},\"Name\":\"address.CountryRegion\"},{\"Measure\":{\"Expression\":{\"SourceRef\":{\"Source\":\"s\"}},\"Property\":\"TotalRevenue\"},\"Name\":\"sales.TotalRevenue\"}],\"OrderBy\":[{\"Direction\":2,\"Expression\":{\"Measure\":{\"Expression\":{\"SourceRef\":{\"Source\":\"s\"}},\"Property\":\"TotalRevenue\"}}}]},\"drillFilterOtherVisuals\":true,\"objects\":{\"categoryAxis\":[{\"properties\":{\"showAxisTitle\":{\"expr\":{\"Literal\":{\"Value\":\"true\"}}}}}],\"valueAxis\":[{\"properties\":{\"showAxisTitle\":{\"expr\":{\"Literal\":{\"Value\":\"true\"}}}}}]},\"vcObjects\":{\"dropShadow\":[{\"properties\":{\"show\":{\"expr\":{\"Literal\":{\"Value\":\"true\"}}},\"color\":{\"solid\":{\"color\":{\"expr\":{\"Literal\":{\"Value\":\"'#A6ADC6'\"}}}}},\"preset\":{\"expr\":{\"Literal\":{\"Value\":\"'Custom'\"}}},\"shadowSpread\":{\"expr\":{\"Literal\":{\"Value\":\"0L\"}}},\"shadowBlur\":{\"expr\":{\"Literal\":{\"Value\":\"5L\"}}},\"angle\":{\"expr\":{\"Literal\":{\"Value\":\"90L\"}}},\"shadowDistance\":{\"expr\":{\"Literal\":{\"Value\":\"4L\"}}},\"transparency\":{\"expr\":{\"Literal\":{\"Value\":\"85L\"}}}}}],\"background\":[{\"properties\":{\"show\":{\"expr\":{\"Literal\":{\"Value\":\"true\"}}}}}],\"border\":[{\"properties\":{\"show\":{\"expr\":{\"Literal\":{\"Value\":\"true\"}}},\"color\":{\"solid\":{\"color\":{\"expr\":{\"Literal\":{\"Value\":\"'#E0E0E0'\"}}}}},\"radius\":{\"expr\":{\"Literal\":{\"Value\":\"4L\"}}}}}],\"title\":[{\"properties\":{\"show\":{\"expr\":{\"Literal\":{\"Value\":\"true\"}}},\"text\":{\"expr\":{\"Literal\":{\"Value\":\"'TotalRevenue by CountryRegion'\"}}}}}]}},\"howCreated\":\"Copilot\"}",
          "filters": "[{\"name\":\"a81556d601300c789209\",\"filter\":{\"Version\":2,\"From\":[{\"Name\":\"a\",\"Entity\":\"address\",\"Type\":0},{\"Name\":\"s\",\"Entity\":\"sales\",\"Type\":0}],\"Where\":[{\"Condition\":{\"Exists\":{\"Expression\":{\"SourceRef\":{\"Source\":\"a\"}}}},\"Target\":[{\"SourceRef\":{\"Source\":\"s\"}}]}]},\"type\":\"Passthrough\",\"restatement\":\"Sales that have addresses\",\"howCreated\":1}]",
          "height": 224.00,
          "width": 595.00,
          "x": 40.00,
          "y": 456.00,
          "z": 1.00
        },
        {
          "config": "{\"name\":\"74777bdf38b205a0c491\",\"layouts\":[{\"id\":0,\"position\":{\"x\":0,\"y\":0,\"z\":1,\"width\":1280,\"height\":80}}],\"singleVisual\":{\"visualType\":\"shape\",\"drillFilterOtherVisuals\":true,\"objects\":{\"fill\":[{\"properties\":{\"show\":{\"expr\":{\"Literal\":{\"Value\":\"false\"}}}}}],\"outline\":[{\"properties\":{\"show\":{\"expr\":{\"Literal\":{\"Value\":\"false\"}}}}}]},\"vcObjects\":{\"dropShadow\":[{\"properties\":{\"show\":{\"expr\":{\"Literal\":{\"Value\":\"true\"}}},\"color\":{\"solid\":{\"color\":{\"expr\":{\"Literal\":{\"Value\":\"'#A6ADC6'\"}}}}},\"preset\":{\"expr\":{\"Literal\":{\"Value\":\"'Custom'\"}}},\"shadowSpread\":{\"expr\":{\"Literal\":{\"Value\":\"0L\"}}},\"shadowBlur\":{\"expr\":{\"Literal\":{\"Value\":\"5L\"}}},\"angle\":{\"expr\":{\"Literal\":{\"Value\":\"90L\"}}},\"shadowDistance\":{\"expr\":{\"Literal\":{\"Value\":\"4L\"}}},\"transparency\":{\"expr\":{\"Literal\":{\"Value\":\"85L\"}}}}}],\"background\":[{\"properties\":{\"show\":{\"expr\":{\"Literal\":{\"Value\":\"true\"}}},\"transparency\":{\"expr\":{\"Literal\":{\"Value\":\"50L\"}}}}}],\"border\":[{\"properties\":{\"show\":{\"expr\":{\"Literal\":{\"Value\":\"true\"}}},\"color\":{\"solid\":{\"color\":{\"expr\":{\"Literal\":{\"Value\":\"'#E0E0E0'\"}}}}},\"radius\":{\"expr\":{\"Literal\":{\"Value\":\"4L\"}}}}}]}},\"howCreated\":\"Copilot\"}",
          "filters": "[]",
          "height": 80.00,
          "width": 1280.00,
          "x": 0.00,
          "y": 0.00,
          "z": 1.00
        },
        {
          "config": "{\"name\":\"8ab4231dcb6186bd55aa\",\"layouts\":[{\"id\":0,\"position\":{\"x\":40,\"y\":20,\"z\":2,\"width\":620,\"height\":40}}],\"singleVisual\":{\"visualType\":\"textbox\",\"drillFilterOtherVisuals\":true,\"objects\":{\"general\":[{\"properties\":{\"paragraphs\":[{\"textRuns\":[{\"value\":\"Overview\",\"textStyle\":{\"fontFamily\":\"Segoe UI\",\"fontSize\":\"14pt\",\"fontWeight\":\"bold\"}}],\"horizontalTextAlignment\":\"left\"}]}}]},\"vcObjects\":{}},\"howCreated\":\"Copilot\"}",
          "filters": "[]",
          "height": 40.00,
          "width": 620.00,
          "x": 40.00,
          "y": 20.00,
          "z": 2.00
        },
        {
          "config": "{\"name\":\"8d0486f64a237ab848e1\",\"layouts\":[{\"id\":0,\"position\":{\"x\":645,\"y\":100,\"z\":1,\"width\":595,\"height\":112}}],\"singleVisual\":{\"visualType\":\"card\",\"projections\":{\"Values\":[{\"queryRef\":\"Sum(sales.OrderQty)\"}]},\"prototypeQuery\":{\"Version\":2,\"From\":[{\"Name\":\"s\",\"Entity\":\"sales\",\"Type\":0}],\"Select\":[{\"Aggregation\":{\"Expression\":{\"Column\":{\"Expression\":{\"SourceRef\":{\"Source\":\"s\"}},\"Property\":\"OrderQty\"}},\"Function\":0},\"Name\":\"Sum(sales.OrderQty)\"}]},\"drillFilterOtherVisuals\":true,\"objects\":{\"labels\":[{\"properties\":{\"labelDisplayUnits\":{\"expr\":{\"Literal\":{\"Value\":\"1L\"}}}}}]},\"vcObjects\":{\"dropShadow\":[{\"properties\":{\"show\":{\"expr\":{\"Literal\":{\"Value\":\"true\"}}},\"color\":{\"solid\":{\"color\":{\"expr\":{\"Literal\":{\"Value\":\"'#A6ADC6'\"}}}}},\"preset\":{\"expr\":{\"Literal\":{\"Value\":\"'Custom'\"}}},\"shadowSpread\":{\"expr\":{\"Literal\":{\"Value\":\"0L\"}}},\"shadowBlur\":{\"expr\":{\"Literal\":{\"Value\":\"5L\"}}},\"angle\":{\"expr\":{\"Literal\":{\"Value\":\"90L\"}}},\"shadowDistance\":{\"expr\":{\"Literal\":{\"Value\":\"4L\"}}},\"transparency\":{\"expr\":{\"Literal\":{\"Value\":\"85L\"}}}}}],\"background\":[{\"properties\":{\"show\":{\"expr\":{\"Literal\":{\"Value\":\"true\"}}}}}],\"border\":[{\"properties\":{\"show\":{\"expr\":{\"Literal\":{\"Value\":\"true\"}}},\"color\":{\"solid\":{\"color\":{\"expr\":{\"Literal\":{\"Value\":\"'#E0E0E0'\"}}}}},\"radius\":{\"expr\":{\"Literal\":{\"Value\":\"4L\"}}}}}]}},\"howCreated\":\"Copilot\"}",
          "filters": "[]",
          "height": 112.00,
          "width": 595.00,
          "x": 645.00,
          "y": 100.00,
          "z": 1.00
        },
        {
          "config": "{\"name\":\"d8f39f2a60bbde34e3ec\",\"layouts\":[{\"id\":0,\"position\":{\"x\":40,\"y\":222,\"z\":1,\"width\":595,\"height\":224}}],\"singleVisual\":{\"visualType\":\"clusteredBarChart\",\"projections\":{\"Category\":[{\"queryRef\":\"product.CategoryName\"}],\"Y\":[{\"queryRef\":\"sales.TotalRevenue\"}]},\"prototypeQuery\":{\"Version\":2,\"From\":[{\"Name\":\"p\",\"Entity\":\"product\",\"Type\":0},{\"Name\":\"s\",\"Entity\":\"sales\",\"Type\":0}],\"Select\":[{\"Column\":{\"Expression\":{\"SourceRef\":{\"Source\":\"p\"}},\"Property\":\"CategoryName\"},\"Name\":\"product.CategoryName\"},{\"Measure\":{\"Expression\":{\"SourceRef\":{\"Source\":\"s\"}},\"Property\":\"TotalRevenue\"},\"Name\":\"sales.TotalRevenue\"}],\"OrderBy\":[{\"Direction\":2,\"Expression\":{\"Measure\":{\"Expression\":{\"SourceRef\":{\"Source\":\"s\"}},\"Property\":\"TotalRevenue\"}}}]},\"drillFilterOtherVisuals\":true,\"objects\":{\"categoryAxis\":[{\"properties\":{\"showAxisTitle\":{\"expr\":{\"Literal\":{\"Value\":\"true\"}}}}}],\"valueAxis\":[{\"properties\":{\"showAxisTitle\":{\"expr\":{\"Literal\":{\"Value\":\"true\"}}}}}]},\"vcObjects\":{\"dropShadow\":[{\"properties\":{\"show\":{\"expr\":{\"Literal\":{\"Value\":\"true\"}}},\"color\":{\"solid\":{\"color\":{\"expr\":{\"Literal\":{\"Value\":\"'#A6ADC6'\"}}}}},\"preset\":{\"expr\":{\"Literal\":{\"Value\":\"'Custom'\"}}},\"shadowSpread\":{\"expr\":{\"Literal\":{\"Value\":\"0L\"}}},\"shadowBlur\":{\"expr\":{\"Literal\":{\"Value\":\"5L\"}}},\"angle\":{\"expr\":{\"Literal\":{\"Value\":\"90L\"}}},\"shadowDistance\":{\"expr\":{\"Literal\":{\"Value\":\"4L\"}}},\"transparency\":{\"expr\":{\"Literal\":{\"Value\":\"85L\"}}}}}],\"background\":[{\"properties\":{\"show\":{\"expr\":{\"Literal\":{\"Value\":\"true\"}}}}}],\"border\":[{\"properties\":{\"show\":{\"expr\":{\"Literal\":{\"Value\":\"true\"}}},\"color\":{\"solid\":{\"color\":{\"expr\":{\"Literal\":{\"Value\":\"'#E0E0E0'\"}}}}},\"radius\":{\"expr\":{\"Literal\":{\"Value\":\"4L\"}}}}}],\"title\":[{\"properties\":{\"show\":{\"expr\":{\"Literal\":{\"Value\":\"true\"}}},\"text\":{\"expr\":{\"Literal\":{\"Value\":\"'TotalRevenue by CategoryName'\"}}}}}]}},\"howCreated\":\"Copilot\"}",
          "filters": "[{\"name\":\"cf921b0fb560d307910c\",\"filter\":{\"Version\":2,\"From\":[{\"Name\":\"p\",\"Entity\":\"product\",\"Type\":0},{\"Name\":\"s\",\"Entity\":\"sales\",\"Type\":0}],\"Where\":[{\"Condition\":{\"Exists\":{\"Expression\":{\"SourceRef\":{\"Source\":\"p\"}}}},\"Target\":[{\"SourceRef\":{\"Source\":\"s\"}}]}]},\"type\":\"Passthrough\",\"restatement\":\"Sales that have products\",\"howCreated\":1}]",
          "height": 224.00,
          "width": 595.00,
          "x": 40.00,
          "y": 222.00,
          "z": 1.00
        },
        {
          "config": "{\"name\":\"dc48a7f984032e09e878\",\"layouts\":[{\"id\":0,\"position\":{\"x\":645,\"y\":222,\"z\":1,\"width\":595,\"height\":224}}],\"singleVisual\":{\"visualType\":\"lineChart\",\"projections\":{\"Series\":[{\"queryRef\":\"date.Month\"}],\"Category\":[{\"queryRef\":\"date.Year\"}],\"Y\":[{\"queryRef\":\"sales.TotalRevenue\"}]},\"prototypeQuery\":{\"Version\":2,\"From\":[{\"Name\":\"d\",\"Entity\":\"date\",\"Type\":0},{\"Name\":\"s\",\"Entity\":\"sales\",\"Type\":0}],\"Select\":[{\"Column\":{\"Expression\":{\"SourceRef\":{\"Source\":\"d\"}},\"Property\":\"Month\"},\"Name\":\"date.Month\"},{\"Column\":{\"Expression\":{\"SourceRef\":{\"Source\":\"d\"}},\"Property\":\"Year\"},\"Name\":\"date.Year\"},{\"Measure\":{\"Expression\":{\"SourceRef\":{\"Source\":\"s\"}},\"Property\":\"TotalRevenue\"},\"Name\":\"sales.TotalRevenue\"}],\"OrderBy\":[{\"Direction\":1,\"Expression\":{\"Column\":{\"Expression\":{\"SourceRef\":{\"Source\":\"d\"}},\"Property\":\"Year\"}}}]},\"drillFilterOtherVisuals\":true,\"objects\":{\"categoryAxis\":[{\"properties\":{\"showAxisTitle\":{\"expr\":{\"Literal\":{\"Value\":\"true\"}}}}}],\"valueAxis\":[{\"properties\":{\"showAxisTitle\":{\"expr\":{\"Literal\":{\"Value\":\"true\"}}}}}]},\"vcObjects\":{\"dropShadow\":[{\"properties\":{\"show\":{\"expr\":{\"Literal\":{\"Value\":\"true\"}}},\"color\":{\"solid\":{\"color\":{\"expr\":{\"Literal\":{\"Value\":\"'#A6ADC6'\"}}}}},\"preset\":{\"expr\":{\"Literal\":{\"Value\":\"'Custom'\"}}},\"shadowSpread\":{\"expr\":{\"Literal\":{\"Value\":\"0L\"}}},\"shadowBlur\":{\"expr\":{\"Literal\":{\"Value\":\"5L\"}}},\"angle\":{\"expr\":{\"Literal\":{\"Value\":\"90L\"}}},\"shadowDistance\":{\"expr\":{\"Literal\":{\"Value\":\"4L\"}}},\"transparency\":{\"expr\":{\"Literal\":{\"Value\":\"85L\"}}}}}],\"background\":[{\"properties\":{\"show\":{\"expr\":{\"Literal\":{\"Value\":\"true\"}}}}}],\"border\":[{\"properties\":{\"show\":{\"expr\":{\"Literal\":{\"Value\":\"true\"}}},\"color\":{\"solid\":{\"color\":{\"expr\":{\"Literal\":{\"Value\":\"'#E0E0E0'\"}}}}},\"radius\":{\"expr\":{\"Literal\":{\"Value\":\"4L\"}}}}}],\"title\":[{\"properties\":{\"show\":{\"expr\":{\"Literal\":{\"Value\":\"true\"}}},\"text\":{\"expr\":{\"Literal\":{\"Value\":\"'TotalRevenue by Year and Month'\"}}}}}]}},\"howCreated\":\"Copilot\"}",
          "filters": "[]",
          "height": 224.00,
          "width": 595.00,
          "x": 645.00,
          "y": 222.00,
          "z": 1.00
        }
      ],
      "width": 1280.00
    },
    {
      "config": "{}",
      "displayName": "Page 1",
      "displayOption": 1,
      "filters": "[]",
      "height": 720.00,
      "name": "ffd51d6aae903d3e500e",
      "visualContainers": [
        {
          "config": "{\"name\":\"37c91f45653c4b53a49d\",\"layouts\":[{\"id\":0,\"position\":{\"x\":10,\"y\":0,\"width\":280,\"height\":280,\"z\":0,\"tabOrder\":0}}],\"singleVisual\":{\"visualType\":\"clusteredColumnChart\",\"projections\":{\"Y\":[{\"queryRef\":\"sales.TotalRevenue\"}],\"Category\":[{\"queryRef\":\"address.StateProvince\",\"active\":true}]},\"prototypeQuery\":{\"Version\":2,\"From\":[{\"Name\":\"s\",\"Entity\":\"sales\",\"Type\":0},{\"Name\":\"a\",\"Entity\":\"address\",\"Type\":0}],\"Select\":[{\"Measure\":{\"Expression\":{\"SourceRef\":{\"Source\":\"s\"}},\"Property\":\"TotalRevenue\"},\"Name\":\"sales.TotalRevenue\",\"NativeReferenceName\":\"TotalRevenue\"},{\"Column\":{\"Expression\":{\"SourceRef\":{\"Source\":\"a\"}},\"Property\":\"StateProvince\"},\"Name\":\"address.StateProvince\",\"NativeReferenceName\":\"StateProvince\"}],\"OrderBy\":[{\"Direction\":2,\"Expression\":{\"Measure\":{\"Expression\":{\"SourceRef\":{\"Source\":\"s\"}},\"Property\":\"TotalRevenue\"}}}]},\"drillFilterOtherVisuals\":true,\"hasDefaultSort\":true}}",
          "filters": "[]",
          "height": 280.00,
          "width": 280.00,
          "x": 10.00,
          "y": 0.00,
          "z": 0.00
        }
      ],
      "width": 1280.00
    }
  ]
}